shellphish_qemu/__init__.py
shellphish_qemu/bin/shellphish-qemu-cgc-base
shellphish_qemu/bin/shellphish-qemu-cgc-nxtracer
shellphish_qemu/bin/shellphish-qemu-cgc-tracer
shellphish_qemu/bin/shellphish-qemu-linux-aarch64
shellphish_qemu/bin/shellphish-qemu-linux-arm
shellphish_qemu/bin/shellphish-qemu-linux-i386
shellphish_qemu/bin/shellphish-qemu-linux-mips
shellphish_qemu/bin/shellphish-qemu-linux-mips64
shellphish_qemu/bin/shellphish-qemu-linux-mipsel
shellphish_qemu/bin/shellphish-qemu-linux-ppc
shellphish_qemu/bin/shellphish-qemu-linux-ppc64
shellphish_qemu/bin/shellphish-qemu-linux-x86_64
shellphish_qemu-0.12.2.dist-info/LICENSE
shellphish_qemu-0.12.2.dist-info/METADATA
shellphish_qemu-0.12.2.dist-info/WHEEL
shellphish_qemu-0.12.2.dist-info/top_level.txt
shellphish_qemu-0.12.2.dist-info/zip-safe
shellphish_qemu-0.12.2.dist-info/RECORD
